MANIFEST.in
README.rst
setup.py
parc_reader/README.md
parc_reader/SETTINGS.py
parc_reader/__init__.py
parc_reader/align_attributions.py
parc_reader/annotated_document.py
parc_reader/attribution.py
parc_reader/attribution_html_serializer.py
parc_reader/bnp_pronouns_reader.py
parc_reader/brat_annotated_text.py
parc_reader/brat_annotation.py
parc_reader/exceptions.py
parc_reader/mention.py
parc_reader/new_parc_annotated_text.py
parc_reader/new_reader.py
parc_reader/parc_annotated_text.py
parc_reader/parc_dataset.py
parc_reader/parc_sentence.py
parc_reader/reader.py
parc_reader/reader_old.py
parc_reader/sentence.py
parc_reader/spans.py
parc_reader/test.py
parc_reader/token_list.py
parc_reader/token_span.py
parc_reader/utils.py
parc_reader.egg-info/PKG-INFO
parc_reader.egg-info/SOURCES.txt
parc_reader.egg-info/dependency_links.txt
parc_reader.egg-info/pbr.json
parc_reader.egg-info/requires.txt
parc_reader.egg-info/top_level.txt
parc_reader/data/example-corenlp-1.xml
parc_reader/data/example-corenlp-2.xml
parc_reader/data/example-parc-1.xml
parc_reader/data/example-parc-2.xml
parc_reader/data/example-parc-output-1.xml
parc_reader/data/example-raw-1.txt
parc_reader/data/example-raw-2.txt
parc_reader/data/test-parc-output-1.xml
parc_reader/data/test-parc-output-2.xml