Metadata-Version: 1.1
Name: parc-reader
Version: 0.1.5
Summary: Work with the PARC dataset in Python
Home-page: https://github.com/enewe101/parc-reader
Author: Edward Newell
Author-email: edward.newell@gmail.com
License: MIT
Keywords: NLP natrual language processing computational linguistics Penn Attribution Relation Corpus PARC PARC3
Platform: UNKNOWN
Classifier: Development Status :: 3 - Alpha
Classifier: Intended Audience :: Developers
Classifier: Topic :: Software Development :: Build Tools
Classifier: License :: OSI Approved :: MIT License
Classifier: Programming Language :: Python :: 2.7
